aursync/__init__.py
aursync/config_proxy.py
aursync/flattener.py
aursync/mpmc.py
aursync/sync.py
aursync-0.0.4.dist-info/METADATA
aursync-0.0.4.dist-info/WHEEL
aursync-0.0.4.dist-info/top_level.txt
aursync-0.0.4.dist-info/RECORD
